LICENSE
MANIFEST.in
README.md
pyproject.toml
setup.py
aws_cdk_bin/__init__.py
aws_cdk_bin/cli.py
aws_cdk_bin/installer.py
aws_cdk_bin/post_install.py
aws_cdk_bin/runtime.py
aws_cdk_bin/version.py
aws_cdk_bin.egg-info/PKG-INFO
aws_cdk_bin.egg-info/SOURCES.txt
aws_cdk_bin.egg-info/dependency_links.txt
aws_cdk_bin.egg-info/entry_points.txt
aws_cdk_bin.egg-info/requires.txt
aws_cdk_bin.egg-info/top_level.txt
aws_cdk_bin/node_modules/aws-cdk/CONTRIBUTING.md
aws_cdk_bin/node_modules/aws-cdk/LICENSE
aws_cdk_bin/node_modules/aws-cdk/NOTICE
aws_cdk_bin/node_modules/aws-cdk/README.md
aws_cdk_bin/node_modules/aws-cdk/THIRD_PARTY_LICENSES
aws_cdk_bin/node_modules/aws-cdk/build-info.json
aws_cdk_bin/node_modules/aws-cdk/db.json.gz
aws_cdk_bin/node_modules/aws-cdk/metadata.json
aws_cdk_bin/node_modules/aws-cdk/package.json
aws_cdk_bin/node_modules/aws-cdk/bin/cdk
aws_cdk_bin/node_modules/aws-cdk/images/garbage-collection.png
aws_cdk_bin/node_modules/aws-cdk/lib/assets.d.ts
aws_cdk_bin/node_modules/aws-cdk/lib/assets.js
aws_cdk_bin/node_modules/aws-cdk/lib/build.d.ts
aws_cdk_bin/node_modules/aws-cdk/lib/build.js
aws_cdk_bin/node_modules/aws-cdk/lib/cdk-toolkit.d.ts
aws_cdk_bin/node_modules/aws-cdk/lib/cdk-toolkit.js
aws_cdk_bin/node_modules/aws-cdk/lib/cli.d.ts
aws_cdk_bin/node_modules/aws-cdk/lib/cli.js
aws_cdk_bin/node_modules/aws-cdk/lib/config.d.ts
aws_cdk_bin/node_modules/aws-cdk/lib/config.js
aws_cdk_bin/node_modules/aws-cdk/lib/convert-to-user-input.d.ts
aws_cdk_bin/node_modules/aws-cdk/lib/convert-to-user-input.js
aws_cdk_bin/node_modules/aws-cdk/lib/diff.d.ts
aws_cdk_bin/node_modules/aws-cdk/lib/diff.js
aws_cdk_bin/node_modules/aws-cdk/lib/import.d.ts
aws_cdk_bin/node_modules/aws-cdk/lib/import.js
aws_cdk_bin/node_modules/aws-cdk/lib/index.d.ts
aws_cdk_bin/node_modules/aws-cdk/lib/index.js
aws_cdk_bin/node_modules/aws-cdk/lib/index_bg.wasm
aws_cdk_bin/node_modules/aws-cdk/lib/init-hooks.d.ts
aws_cdk_bin/node_modules/aws-cdk/lib/init-hooks.js
aws_cdk_bin/node_modules/aws-cdk/lib/init.d.ts
aws_cdk_bin/node_modules/aws-cdk/lib/init.js
aws_cdk_bin/node_modules/aws-cdk/lib/list-stacks.d.ts
aws_cdk_bin/node_modules/aws-cdk/lib/list-stacks.js
